winrt/_winrt_windows_ui_xaml.cp313-win_amd64.pyd
winrt/_winrt_windows_ui_xaml.pyi
winrt/windows/ui/xaml/__init__.py
winrt/windows/ui/xaml/py.typed
winrt_windows_ui_xaml-3.2.1.dist-info/METADATA
winrt_windows_ui_xaml-3.2.1.dist-info/WHEEL
winrt_windows_ui_xaml-3.2.1.dist-info/top_level.txt
winrt_windows_ui_xaml-3.2.1.dist-info/RECORD
