Metadata-Version: 2.4
Name: winrt-Windows.UI.Xaml
Version: 3.2.1
Summary: Python projection of Windows Runtime (WinRT) APIs
License-Expression: MIT
Project-URL: Documentation, https://pywinrt.readthedocs.io
Project-URL: Repository, https://github.com/pywinrt/pywinrt
Project-URL: Changelog, https://github.com/pywinrt/pywinrt/blob/main/CHANGELOG.md
Classifier: Operating System :: Microsoft :: Windows
Classifier: Programming Language :: Python :: 3
Classifier: Programming Language :: Python :: Implementation :: CPython
Classifier: Intended Audience :: Developers
Requires-Python: >=3.9
Requires-Dist: winrt-runtime~=3.2.1.0
Provides-Extra: all
Requires-Dist: winrt-Windows.ApplicationModel[all]~=3.2.1.0; extra == "all"
Requires-Dist: winrt-Windows.ApplicationModel.Activation[all]~=3.2.1.0; extra == "all"
Requires-Dist: winrt-Windows.ApplicationModel.Core[all]~=3.2.1.0; extra == "all"
Requires-Dist: winrt-Windows.ApplicationModel.DataTransfer[all]~=3.2.1.0; extra == "all"
Requires-Dist: winrt-Windows.ApplicationModel.DataTransfer.DragDrop[all]~=3.2.1.0; extra == "all"
Requires-Dist: winrt-Windows.Foundation[all]~=3.2.1.0; extra == "all"
Requires-Dist: winrt-Windows.Foundation.Collections[all]~=3.2.1.0; extra == "all"
Requires-Dist: winrt-Windows.Foundation.Numerics[all]~=3.2.1.0; extra == "all"
Requires-Dist: winrt-Windows.Graphics.Imaging[all]~=3.2.1.0; extra == "all"
Requires-Dist: winrt-Windows.UI[all]~=3.2.1.0; extra == "all"
Requires-Dist: winrt-Windows.UI.Composition[all]~=3.2.1.0; extra == "all"
Requires-Dist: winrt-Windows.UI.Core[all]~=3.2.1.0; extra == "all"
Requires-Dist: winrt-Windows.UI.Input[all]~=3.2.1.0; extra == "all"
Requires-Dist: winrt-Windows.UI.Xaml.Automation.Peers[all]~=3.2.1.0; extra == "all"
Requires-Dist: winrt-Windows.UI.Xaml.Controls[all]~=3.2.1.0; extra == "all"
Requires-Dist: winrt-Windows.UI.Xaml.Controls.Primitives[all]~=3.2.1.0; extra == "all"
Requires-Dist: winrt-Windows.UI.Xaml.Data[all]~=3.2.1.0; extra == "all"
Requires-Dist: winrt-Windows.UI.Xaml.Input[all]~=3.2.1.0; extra == "all"
Requires-Dist: winrt-Windows.UI.Xaml.Interop[all]~=3.2.1.0; extra == "all"
Requires-Dist: winrt-Windows.UI.Xaml.Media[all]~=3.2.1.0; extra == "all"
Requires-Dist: winrt-Windows.UI.Xaml.Media.Animation[all]~=3.2.1.0; extra == "all"
Requires-Dist: winrt-Windows.UI.Xaml.Media.Imaging[all]~=3.2.1.0; extra == "all"
Requires-Dist: winrt-Windows.UI.Xaml.Media.Media3D[all]~=3.2.1.0; extra == "all"
